oflo_agent_protocol/__init__.py
oflo_agent_protocol/agent.py
oflo_agent_protocol/cmo.py
oflo_agent_protocol/factory.py
oflo_agent_protocol/mcp.py
oflo_agent_protocol/resource.py
oflo_agent_protocol/tool.py
oflo_agent_protocol/adapters/crewai_adapter.py
oflo_agent_protocol/adapters/langgraph_adapter.py
oflo_ai_agent_protocol-0.1.0.dist-info/licenses/LICENSE
oflo_ai_agent_protocol-0.1.0.dist-info/METADATA
oflo_ai_agent_protocol-0.1.0.dist-info/WHEEL
oflo_ai_agent_protocol-0.1.0.dist-info/top_level.txt
oflo_ai_agent_protocol-0.1.0.dist-info/RECORD
