Metadata-Version: 2.4
Name: oflo-ai-agent-protocol
Version: 0.1.0
Summary: A protocol for building business AI agents with MCP integration
Home-page: https://github.com/ankitbuti/oflo-agent-protocol
Author: Ankit Buti
Author-email: Ankit Buti <ankit@oflo.ai>
License: MIT License
Classifier: Development Status :: 3 - Alpha
Classifier: Intended Audience :: Developers
Classifier: License :: OSI Approved :: MIT License
Classifier: Operating System :: OS Independent
Classifier: Programming Language :: Python :: 3
Classifier: Programming Language :: Python :: 3.8
Classifier: Programming Language :: Python :: 3.9
Classifier: Programming Language :: Python :: 3.10
Classifier: Programming Language :: Python :: 3.11
Requires-Python: >=3.8
License-File: LICENSE
Requires-Dist: aiohttp>=3.8.0
Requires-Dist: anthropic>=0.8.0
Requires-Dist: openai>=1.3.0
Requires-Dist: pydantic>=2.0.0
Requires-Dist: python-dotenv>=1.0.0
Requires-Dist: slack-sdk>=3.19.0
Requires-Dist: typing-extensions>=4.0.0
Requires-Dist: cloudflare>=2.8.0
Requires-Dist: weaviate-client>=3.24.1
Requires-Dist: crewai>=0.11.0
Requires-Dist: langchain>=0.1.0
Requires-Dist: langgraph>=0.0.15
Requires-Dist: langchain-core>=0.1.0
Requires-Dist: mcp-python-sdk>=0.1.0
Provides-Extra: dev
Requires-Dist: pytest>=7.0.0; extra == "dev"
Requires-Dist: pytest-asyncio>=0.20.0; extra == "dev"
Requires-Dist: pytest-cov>=4.0.0; extra == "dev"
Requires-Dist: black>=22.0.0; extra == "dev"
Requires-Dist: isort>=5.0.0; extra == "dev"
Requires-Dist: mypy>=1.0.0; extra == "dev"
Requires-Dist: flake8>=6.0.0; extra == "dev"
Requires-Dist: build>=0.7.0; extra == "dev"
Requires-Dist: twine>=4.0.0; extra == "dev"
Provides-Extra: docs
Requires-Dist: sphinx>=4.0.0; extra == "docs"
Requires-Dist: sphinx-rtd-theme>=1.0.0; extra == "docs"
Requires-Dist: myst-parser>=1.0.0; extra == "docs"
Dynamic: author
Dynamic: home-page
Dynamic: license-file
Dynamic: requires-python
